sentry_redis_tools/__init__.py
sentry_redis_tools/cardinality_limiter.py
sentry_redis_tools/clients.py
sentry_redis_tools/failover_redis.py
sentry_redis_tools/metrics.py
sentry_redis_tools/py.typed
sentry_redis_tools/retrying_cluster.py
sentry_redis_tools/sliding_windows_rate_limiter.py
sentry_redis_tools-0.5.1.dist-info/LICENSE
sentry_redis_tools-0.5.1.dist-info/METADATA
sentry_redis_tools-0.5.1.dist-info/WHEEL
sentry_redis_tools-0.5.1.dist-info/top_level.txt
sentry_redis_tools-0.5.1.dist-info/RECORD
