Metadata-Version: 2.1
Name: sentry-redis-tools
Version: 0.5.1
Summary: Common utilities related to how Sentry uses Redis
Home-page: https://github.com/getsentry/sentry-redis-tools
Author: Sentry
Author-email: oss@sentry.io
License: Apache-2.0
Platform: UNKNOWN
Requires-Dist: redis>=3.0
Provides-Extra: cluster
Requires-Dist: redis-py-cluster>=2.1.0; extra == "cluster"
